flake8_boto3/__init__.py
flake8_boto3/auth.py
flake8_boto3/boto_import.py
flake8_boto3/deprecated.py
flake8_boto3/main.py
flake8_boto3-0.3.0.dist-info/entry_points.txt
flake8_boto3-0.3.0.dist-info/WHEEL
flake8_boto3-0.3.0.dist-info/METADATA
flake8_boto3-0.3.0.dist-info/RECORD
