Metadata-Version: 2.1
Name: flake8-boto3
Version: 0.3.0
Summary: Checks for boto3, by r2c. Available in [Bento](https://bento.dev).
Home-page: https://bento.dev
Author: R2C
Author-email: hello@returntocorp.com
Requires-Python: >=3.6,<4.0
Classifier: License :: Other/Proprietary License
Classifier: Operating System :: OS Independent
Classifier: Programming Language :: Python :: 3
Classifier: Programming Language :: Python :: 3.6
Classifier: Programming Language :: Python :: 3.7
Classifier: Programming Language :: Python :: 3.8
Requires-Dist: boto3 (>=1.10.21,<2.0.0)
Requires-Dist: flake8 (>=3.7.9,<4.0.0)
Requires-Dist: r2c-py-ast (==0.1.0b1)
